frameutils/__init__.py
frameutils/bluetooth.py
frameutils/cli.py
frameutils/create_sprites.py
frameutils-0.1.15.dist-info/METADATA
frameutils-0.1.15.dist-info/WHEEL
frameutils-0.1.15.dist-info/entry_points.txt
frameutils-0.1.15.dist-info/RECORD
