Metadata-Version: 2.3
Name: frameutils
Version: 0.1.15
Summary: Useful utilities for your Brilliant Frame AR glasses
Project-URL: Homepage, https://github.com/brilliantlabsAR/frame-utilities-for-python
Project-URL: Bug Tracker, https://github.com/brilliantlabsAR/frame-utilities-for-python/issues
Author-email: Brilliant Labs <info@brilliant.xyz>
License: ISC License
Classifier: Operating System :: OS Independent
Classifier: Programming Language :: Python :: 3
Requires-Python: >=3.7
Requires-Dist: bleak
Requires-Dist: numpy
Requires-Dist: scikit-learn
